datasette_tiles/__init__.py
datasette_tiles/utils.py
datasette_tiles/templates/tiles_explorer.html
datasette_tiles/templates/tiles_index.html
datasette_tiles/templates/tiles_stack_explorer.html
datasette_tiles-0.6.1.dist-info/METADATA
datasette_tiles-0.6.1.dist-info/WHEEL
datasette_tiles-0.6.1.dist-info/entry_points.txt
datasette_tiles-0.6.1.dist-info/top_level.txt
datasette_tiles-0.6.1.dist-info/RECORD
