Metadata-Version: 2.1
Name: datasette-tiles
Version: 0.6.1
Summary: Mapping tile server for Datasette, serving tiles from MBTiles packages
Home-page: https://github.com/simonw/datasette-tiles
Author: Simon Willison
License: Apache License, Version 2.0
Project-URL: Issues, https://github.com/simonw/datasette-tiles/issues
Project-URL: CI, https://github.com/simonw/datasette-tiles/actions
Project-URL: Changelpog, https://github.com/simonw/datasette-tiles/releases
Platform: UNKNOWN
Requires-Python: >=3.6
Requires-Dist: datasette
Requires-Dist: datasette-leaflet (>=0.2.2)
Provides-Extra: test
Requires-Dist: pytest ; extra == 'test'
Requires-Dist: pytest-asyncio ; extra == 'test'
Requires-Dist: datasette-basemap (>=0.2) ; extra == 'test'
